Workbook

Sheet Events
A1: Event | B1: City | C1: Event Date | D1: Genre | E1: Ticket Price (euro) | F1: Margin % | G1: Margin Eros | H1: Ticket Category | I1: Tickets Available | J1: Rating | K1: Tickets Sold | L1: Description | M1: Days | N1: Margin Euros | O1: Tickekt Code
A2: Aida | B2: Vienna | C2: 42896 | D2: Opera | E2: 70 | F2: =IFERROR(VLOOKUP(E2,Margins!$A:$B,2,TRUE),"") -> 0.1 | G2: =IFERROR(E2*F2*I2,"") -> 21000 | H2: SC1 | I2: 3000 | J2: =IF(Table1[[#This Row],[Tickets Sold]]>500,8,5) -> 8 | K2: 1680 | L2: =VLOOKUP(H2,Descriptions!A:B, 2, FALSE) -> Seating Cat. 1 | M2: =NETWORKDAYS(TODAY(), C2-1) -> -2300 | N2: =E2*F2*K2 -> 11760 | O2: =RIGHT(YEAR(Table1[[#This Row],[Event Date]]),2)&"-"&Table1[[#This Row],[Ticket Category]]&LEFT(Table1[[#This Row],[Event]],3)&"-"&LEFT(Table1[[#This Row],[City]],3)&DAY(Table1[[#This Row],[Event Date]])&"/"&MONTH(Table1[[#This Row],[Event Date]]) -> 17-SC1Aid-Vie10/6
A3: Aida | B3: Vienna | C3: 42896 | D3: Opera | E3: 84 | F3: =IFERROR(VLOOKUP(E3,Margins!$A:$B,2,TRUE),"") -> 0.1 | G3: =IFERROR(E3*F3*I3,"") -> 8400 | H3: SC2 | I3: 1000 | J3: =IF(Table1[[#This Row],[Tickets Sold]]>500,8,5) -> 8 | K3: 740 | L3: =VLOOKUP(H3,Descriptions!A:B, 2, FALSE) -> Seating Cat. 2 | M3: =NETWORKDAYS(TODAY(), C3-1) -> -2300 | O3: =RIGHT(YEAR(Table1[[#This Row],[Event Date]]),2)&"-"&Table1[[#This Row],[Ticket Category]]&LEFT(Table1[[#This Row],[Event]],3)&"-"&LEFT(Table1[[#This Row],[City]],3)&DAY(Table1[[#This Row],[Event Date]])&"/"&MONTH(Table1[[#This Row],[Event Date]]) -> 17-SC2Aid-Vie10/6
A4: Aida | B4: Vienna | C4: 42896 | D4: Opera | E4: 121 | F4: =IFERROR(VLOOKUP(E4,Margins!$A:$B,2,TRUE),"") -> 0.15 | G4: =IFERROR(E4*F4*I4,"") -> 9075 | H4: SC3 | I4: 500 | J4: =IF(Table1[[#This Row],[Tickets Sold]]>500,8,5) -> 5 | K4: 250 | L4: =VLOOKUP(H4,Descriptions!A:B, 2, FALSE) -> Seating Cat. 3 | M4: =NETWORKDAYS(TODAY(), C4-1) -> -2300 | O4: =RIGHT(YEAR(Table1[[#This Row],[Event Date]]),2)&"-"&Table1[[#This Row],[Ticket Category]]&LEFT(Table1[[#This Row],[Event]],3)&"-"&LEFT(Table1[[#This Row],[City]],3)&DAY(Table1[[#This Row],[Event Date]])&"/"&MONTH(Table1[[#This Row],[Event Date]]) -> 17-SC3Aid-Vie10/6
A5: Aida | B5: Vienna | C5: 42896 | D5: Opera | E5: 272 | F5: =IFERROR(VLOOKUP(E5,Margins!$A:$B,2,TRUE),"") -> 0.25 | G5: =IFERROR(E5*F5*I5,"") -> 20400 | H5: TA1 | I5: 300 | J5: =IF(Table1[[#This Row],[Tickets Sold]]>500,8,5) -> 5 | K5: 198 | L5: =VLOOKUP(H5,Descriptions!A:B, 2, FALSE) -> Ticket + Air travel Package | M5: =NETWORKDAYS(TODAY(), C5-1) -> -2300 | O5: =RIGHT(YEAR(Table1[[#This Row],[Event Date]]),2)&"-"&Table1[[#This Row],[Ticket Category]]&LEFT(Table1[[#This Row],[Event]],3)&"-"&LEFT(Table1[[#This Row],[City]],3)&DAY(Table1[[#This Row],[Event Date]])&"/"&MONTH(Table1[[#This Row],[Event Date]]) -> 17-TA1Aid-Vie10/6
A6: Aida | B6: Vienna | C6: 42896 | D6: Opera | E6: 370 | F6: =IFERROR(VLOOKUP(E6,Margins!$A:$B,2,TRUE),"") -> 0.25 | G6: =IFERROR(E6*F6*I6,"") -> 37000 | H6: TA2 | I6: 400 | J6: =IF(Table1[[#This Row],[Tickets Sold]]>500,8,5) -> 5 | K6: 324 | L6: =VLOOKUP(H6,Descriptions!A:B, 2, FALSE) -> Ticket + Air travel + Hotel Package | M6: =NETWORKDAYS(TODAY(), C6-1) -> -2300 | O6: =RIGHT(YEAR(Table1[[#This Row],[Event Date]]),2)&"-"&Table1[[#This Row],[Ticket Category]]&LEFT(Table1[[#This Row],[Event]],3)&"-"&LEFT(Table1[[#This Row],[City]],3)&DAY(Table1[[#This Row],[Event Date]])&"/"&MONTH(Table1[[#This Row],[Event Date]]) -> 17-TA2Aid-Vie10/6
A7: Aida | B7: Madrid | C7: 42904 | D7: Opera | E7: 31 | F7: =IFERROR(VLOOKUP(E7,Margins!$A:$B,2,TRUE),"") -> 0.07 | G7: =IFERROR(E7*F7*I7,"") -> 8680 | H7: SC1 | I7: 4000 | J7: =IF(Table1[[#This Row],[Tickets Sold]]>500,8,5) -> 8 | K7: 2800 | L7: =VLOOKUP(H7,Descriptions!A:B, 2, FALSE) -> Seating Cat. 1 | M7: =NETWORKDAYS(TODAY(), C7-1) -> -2294 | O7: =RIGHT(YEAR(Table1[[#This Row],[Event Date]]),2)&"-"&Table1[[#This Row],[Ticket Category]]&LEFT(Table1[[#This Row],[Event]],3)&"-"&LEFT(Table1[[#This Row],[City]],3)&DAY(Table1[[#This Row],[Event Date]])&"/"&MONTH(Table1[[#This Row],[Event Date]]) -> 17-SC1Aid-Mad18/6
A8: Aida | B8: Madrid | C8: 42904 | D8: Opera | E8: 93 | F8: =IFERROR(VLOOKUP(E8,Margins!$A:$B,2,TRUE),"") -> 0.1 | G8: =IFERROR(E8*F8*I8,"") -> 11160 | H8: SC2 | I8: 1200 | J8: =IF(Table1[[#This Row],[Tickets Sold]]>500,8,5) -> 8 | K8: 1044 | L8: =VLOOKUP(H8,Descriptions!A:B, 2, FALSE) -> Seating Cat. 2 | M8: =NETWORKDAYS(TODAY(), C8-1) -> -2294 | O8: =RIGHT(YEAR(Table1[[#This Row],[Event Date]]),2)&"-"&Table1[[#This Row],[Ticket Category]]&LEFT(Table1[[#This Row],[Event]],3)&"-"&LEFT(Table1[[#This Row],[City]],3)&DAY(Table1[[#This Row],[Event Date]])&"/"&MONTH(Table1[[#This Row],[Event Date]]) -> 17-SC2Aid-Mad18/6
A9: Aida | B9: Madrid | C9: 42904 | D9: Opera | E9: 189 | F9: =IFERROR(VLOOKUP(E9,Margins!$A:$B,2,TRUE),"") -> 0.15 | G9: =IFERROR(E9*F9*I9,"") -> 19845 | H9: SC3 | I9: 700 | J9: =IF(Table1[[#This Row],[Tickets Sold]]>500,8,5) -> 8 | K9: 630 | L9: =VLOOKUP(H9,Descriptions!A:B, 2, FALSE) -> Seating Cat. 3 | M9: =NETWORKDAYS(TODAY(), C9-1) -> -2294 | O9: =RIGHT(YEAR(Table1[[#This Row],[Event Date]]),2)&"-"&Table1[[#This Row],[Ticket Category]]&LEFT(Table1[[#This Row],[Event]],3)&"-"&LEFT(Table1[[#This Row],[City]],3)&DAY(Table1[[#This Row],[Event Date]])&"/"&MONTH(Table1[[#This Row],[Event Date]]) -> 17-SC3Aid-Mad18/6
A10: Aida | B10: Stockholm | C10: 42910 | D10: Opera | E10: 59 | F10: =IFERROR(VLOOKUP(E10,Margins!$A:$B,2,TRUE),"") -> 0.1 | G10: =IFERROR(E10*F10*I10,"") -> 11800 | H10: SC1 | I10: 2000 | J10: =IF(Table1[[#This Row],[Tickets Sold]]>500,8,5) -> 8 | K10: 1520 | L10: =VLOOKUP(H10,Descriptions!A:B, 2, FALSE) -> Seating Cat. 1 | M10: =NETWORKDAYS(TODAY(), C10-1) -> -2290 | O10: =RIGHT(YEAR(Table1[[#This Row],[Event Date]]),2)&"-"&Table1[[#This Row],[Ticket Category]]&LEFT(Table1[[#This Row],[Event]],3)&"-"&LEFT(Table1[[#This Row],[City]],3)&DAY(Table1[[#This Row],[Event Date]])&"/"&MONTH(Table1[[#This Row],[Event Date]]) -> 17-SC1Aid-Sto24/6
A11: Aida | B11: Stockholm | C11: 42910 | D11: Opera | E11: 93 | F11: =IFERROR(VLOOKUP(E11,Margins!$A:$B,2,TRUE),"") -> 0.1 | G11: =IFERROR(E11*F11*I11,"") -> 8370 | H11: SC2 | I11: 900 | J11: =IF(Table1[[#This Row],[Tickets Sold]]>500,8,5) -> 8 | K11: 513 | L11: =VLOOKUP(H11,Descriptions!A:B, 2, FALSE) -> Seating Cat. 2 | M11: =NETWORKDAYS(TODAY(), C11-1) -> -2290 | O11: =RIGHT(YEAR(Table1[[#This Row],[Event Date]]),2)&"-"&Table1[[#This Row],[Ticket Category]]&LEFT(Table1[[#This Row],[Event]],3)&"-"&LEFT(Table1[[#This Row],[City]],3)&DAY(Table1[[#This Row],[Event Date]])&"/"&MONTH(Table1[[#This Row],[Event Date]]) -> 17-SC2Aid-Sto24/6
A12: Aida | B12: Stockholm | C12: 42910 | D12: Opera | E12: 168 | F12: =IFERROR(VLOOKUP(E12,Margins!$A:$B,2,TRUE),"") -> 0.15 | G12: =IFERROR(E12*F12*I12,"") -> 11340 | H12: SC3 | I12: 450 | J12: =IF(Table1[[#This Row],[Tickets Sold]]>500,8,5) -> 5 | K12: 356 | L12: =VLOOKUP(H12,Descriptions!A:B, 2, FALSE) -> Seating Cat. 3 | M12: =NETWORKDAYS(TODAY(), C12-1) -> -2290 | O12: =RIGHT(YEAR(Table1[[#This Row],[Event Date]]),2)&"-"&Table1[[#This Row],[Ticket Category]]&LEFT(Table1[[#This Row],[Event]],3)&"-"&LEFT(Table1[[#This Row],[City]],3)&DAY(Table1[[#This Row],[Event Date]])&"/"&MONTH(Table1[[#This Row],[Event Date]]) -> 17-SC3Aid-Sto24/6
A13: Aida | B13: Stockholm | C13: 42910 | D13: Opera | E13: 283 | F13: =IFERROR(VLOOKUP(E13,Margins!$A:$B,2,TRUE),"") -> 0.25 | G13: =IFERROR(E13*F13*I13,"") -> 21225 | H13: TA1 | I13: 300 | J13: =IF(Table1[[#This Row],[Tickets Sold]]>500,8,5) -> 5 | K13: 231 | L13: =VLOOKUP(H13,Descriptions!A:B, 2, FALSE) -> Ticket + Air travel Package | M13: =NETWORKDAYS(TODAY(), C13-1) -> -2290 | O13: =RIGHT(YEAR(Table1[[#This Row],[Event Date]]),2)&"-"&Table1[[#This Row],[Ticket Category]]&LEFT(Table1[[#This Row],[Event]],3)&"-"&LEFT(Table1[[#This Row],[City]],3)&DAY(Table1[[#This Row],[Event Date]])&"/"&MONTH(Table1[[#This Row],[Event Date]]) -> 17-TA1Aid-Sto24/6
A14: Aida | B14: Stockholm | C14: 42910 | D14: Opera | E14: 363 | F14: =IFERROR(VLOOKUP(E14,Margins!$A:$B,2,TRUE),"") -> 0.25 | G14: =IFERROR(E14*F14*I14,"") -> 36300 | H14: TA2 | I14: 400 | J14: =IF(Table1[[#This Row],[Tickets Sold]]>500,8,5) -> 5 | K14: 320 | L14: =VLOOKUP(H14,Descriptions!A:B, 2, FALSE) -> Ticket + Air travel + Hotel Package | M14: =NETWORKDAYS(TODAY(), C14-1) -> -2290 | O14: =RIGHT(YEAR(Table1[[#This Row],[Event Date]]),2)&"-"&Table1[[#This Row],[Ticket Category]]&LEFT(Table1[[#This Row],[Event]],3)&"-"&LEFT(Table1[[#This Row],[City]],3)&DAY(Table1[[#This Row],[Event Date]])&"/"&MONTH(Table1[[#This Row],[Event Date]]) -> 17-TA2Aid-Sto24/6
... A189: Lo schiaccianoci | B189: Amsterdam | C189: 42973 | D189: Ballet | E189: 330 | F189: =IFERROR(VLOOKUP(E189,Margins!$A:$B,2,TRUE),"") -> 0.25 | G189: =IFERROR(E189*F189*I189,"") -> 24750 | H189: TA2 | I189: 300 | J189: =IF(Table1[[#This Row],[Tickets Sold]]>500,8,5) -> 5 | K189: 159 | L189: =VLOOKUP(H189,Descriptions!A:B, 2, FALSE) -> Ticket + Air travel + Hotel Package | M189: =NETWORKDAYS(TODAY(), C189-1) -> -2245 | O189: =RIGHT(YEAR(Table1[[#This Row],[Event Date]]),2)&"-"&Table1[[#This Row],[Ticket Category]]&LEFT(Table1[[#This Row],[Event]],3)&"-"&LEFT(Table1[[#This Row],[City]],3)&DAY(Table1[[#This Row],[Event Date]])&"/"&MONTH(Table1[[#This Row],[Event Date]]) -> 17-TA2Lo -Ams26/8
A190: London Blues Fest | B190: London | C190: 42891 | D190: Festival | F190: =IFERROR(VLOOKUP(E190,Margins!$A:$B,2,TRUE),"") | G190: =IFERROR(E190*F190*I190,"") | H190: GA1 | I190: 75000 | J190: =IF(Table1[[#This Row],[Tickets Sold]]>500,8,5) -> 8 | K190: 48000 | L190: =VLOOKUP(H190,Descriptions!A:B, 2, FALSE) -> General Admission (1 day) | M190: =NETWORKDAYS(TODAY(), C190-1) -> -2304 | O190: =RIGHT(YEAR(Table1[[#This Row],[Event Date]]),2)&"-"&Table1[[#This Row],[Ticket Category]]&LEFT(Table1[[#This Row],[Event]],3)&"-"&LEFT(Table1[[#This Row],[City]],3)&DAY(Table1[[#This Row],[Event Date]])&"/"&MONTH(Table1[[#This Row],[Event Date]]) -> 17-GA1Lon-Lon5/6
A191: London Blues Fest | B191: London | C191: 42891 | D191: Festival | E191: 78 | F191: =IFERROR(VLOOKUP(E191,Margins!$A:$B,2,TRUE),"") -> 0.1 | G191: =IFERROR(E191*F191*I191,"") -> 19500 | H191: SC1 | I191: 2500 | J191: =IF(Table1[[#This Row],[Tickets Sold]]>500,8,5) -> 8 | K191: 2275 | L191: =VLOOKUP(H191,Descriptions!A:B, 2, FALSE) -> Seating Cat. 1 | M191: =NETWORKDAYS(TODAY(), C191-1) -> -2304 | O191: =RIGHT(YEAR(Table1[[#This Row],[Event Date]]),2)&"-"&Table1[[#This Row],[Ticket Category]]&LEFT(Table1[[#This Row],[Event]],3)&"-"&LEFT(Table1[[#This Row],[City]],3)&DAY(Table1[[#This Row],[Event Date]])&"/"&MONTH(Table1[[#This Row],[Event Date]]) -> 17-SC1Lon-Lon5/6
A192: London Blues Fest | B192: London | C192: 42891 | D192: Festival | F192: =IFERROR(VLOOKUP(E192,Margins!$A:$B,2,TRUE),"") | G192: =IFERROR(E192*F192*I192,"") | H192: GA3 | I192: 75000 | J192: =IF(Table1[[#This Row],[Tickets Sold]]>500,8,5) -> 8 | K192: 47250 | L192: =VLOOKUP(H192,Descriptions!A:B, 2, FALSE) -> General Admission (season ticket) | M192: =NETWORKDAYS(TODAY(), C192-1) -> -2304 | O192: =RIGHT(YEAR(Table1[[#This Row],[Event Date]]),2)&"-"&Table1[[#This Row],[Ticket Category]]&LEFT(Table1[[#This Row],[Event]],3)&"-"&LEFT(Table1[[#This Row],[City]],3)&DAY(Table1[[#This Row],[Event Date]])&"/"&MONTH(Table1[[#This Row],[Event Date]]) -> 17-GA3Lon-Lon5/6
A193: London Blues Fest | B193: London | C193: 42891 | D193: Festival | E193: 28 | F193: =IFERROR(VLOOKUP(E193,Margins!$A:$B,2,TRUE),"") -> 0.07 | G193: =IFERROR(E193*F193*I193,"") -> 225.4 | H193: SCD | I193: 115 | J193: =IF(Table1[[#This Row],[Tickets Sold]]>500,8,5) -> 5 | K193: 92 | L193: =VLOOKUP(H193,Descriptions!A:B, 2, FALSE) -> Seating-disabled | M193: =NETWORKDAYS(TODAY(), C193-1) -> -2304 | O193: =RIGHT(YEAR(Table1[[#This Row],[Event Date]]),2)&"-"&Table1[[#This Row],[Ticket Category]]&LEFT(Table1[[#This Row],[Event]],3)&"-"&LEFT(Table1[[#This Row],[City]],3)&DAY(Table1[[#This Row],[Event Date]])&"/"&MONTH(Table1[[#This Row],[Event Date]]) -> 17-SCDLon-Lon5/6
A194: London Blues Fest | B194: London | C194: 42892 | D194: Festival | F194: =IFERROR(VLOOKUP(E194,Margins!$A:$B,2,TRUE),"") | G194: =IFERROR(E194*F194*I194,"") | H194: GA1 | I194: 75000 | J194: =IF(Table1[[#This Row],[Tickets Sold]]>500,8,5) -> 8 | K194: 70500 | L194: =VLOOKUP(H194,Descriptions!A:B, 2, FALSE) -> General Admission (1 day) | M194: =NETWORKDAYS(TODAY(), C194-1) -> -2304 | O194: =RIGHT(YEAR(Table1[[#This Row],[Event Date]]),2)&"-"&Table1[[#This Row],[Ticket Category]]&LEFT(Table1[[#This Row],[Event]],3)&"-"&LEFT(Table1[[#This Row],[City]],3)&DAY(Table1[[#This Row],[Event Date]])&"/"&MONTH(Table1[[#This Row],[Event Date]]) -> 17-GA1Lon-Lon6/6
A195: London Blues Fest | B195: London | C195: 42892 | D195: Festival | E195: 77 | F195: =IFERROR(VLOOKUP(E195,Margins!$A:$B,2,TRUE),"") -> 0.1 | G195: =IFERROR(E195*F195*I195,"") -> 19250 | H195: SC1 | I195: 2500 | J195: =IF(Table1[[#This Row],[Tickets Sold]]>500,8,5) -> 8 | K195: 1750 | L195: =VLOOKUP(H195,Descriptions!A:B, 2, FALSE) -> Seating Cat. 1 | M195: =NETWORKDAYS(TODAY(), C195-1) -> -2304 | O195: =RIGHT(YEAR(Table1[[#This Row],[Event Date]]),2)&"-"&Table1[[#This Row],[Ticket Category]]&LEFT(Table1[[#This Row],[Event]],3)&"-"&LEFT(Table1[[#This Row],[City]],3)&DAY(Table1[[#This Row],[Event Date]])&"/"&MONTH(Table1[[#This Row],[Event Date]]) -> 17-SC1Lon-Lon6/6
A196: London Blues Fest | B196: London | C196: 42892 | D196: Festival | E196: 22 | F196: =IFERROR(VLOOKUP(E196,Margins!$A:$B,2,TRUE),"") -> 0.07 | G196: =IFERROR(E196*F196*I196,"") -> 184.8 | H196: SCD | I196: 120 | J196: =IF(Table1[[#This Row],[Tickets Sold]]>500,8,5) -> 5 | K196: 90 | L196: =VLOOKUP(H196,Descriptions!A:B, 2, FALSE) -> Seating-disabled | M196: =NETWORKDAYS(TODAY(), C196-1) -> -2304 | O196: =RIGHT(YEAR(Table1[[#This Row],[Event Date]]),2)&"-"&Table1[[#This Row],[Ticket Category]]&LEFT(Table1[[#This Row],[Event]],3)&"-"&LEFT(Table1[[#This Row],[City]],3)&DAY(Table1[[#This Row],[Event Date]])&"/"&MONTH(Table1[[#This Row],[Event Date]]) -> 17-SCDLon-Lon6/6
A197: London Blues Fest | B197: London | C197: 42892 | D197: Festival | E197: 247 | F197: =IFERROR(VLOOKUP(E197,Margins!$A:$B,2,TRUE),"") -> 0.25 | G197: =IFERROR(E197*F197*I197,"") -> 12350 | H197: TA1 | I197: 200 | J197: =IF(Table1[[#This Row],[Tickets Sold]]>500,8,5) -> 5 | K197: 158 | L197: =VLOOKUP(H197,Descriptions!A:B, 2, FALSE) -> Ticket + Air travel Package | M197: =NETWORKDAYS(TODAY(), C197-1) -> -2304 | O197: =RIGHT(YEAR(Table1[[#This Row],[Event Date]]),2)&"-"&Table1[[#This Row],[Ticket Category]]&LEFT(Table1[[#This Row],[Event]],3)&"-"&LEFT(Table1[[#This Row],[City]],3)&DAY(Table1[[#This Row],[Event Date]])&"/"&MONTH(Table1[[#This Row],[Event Date]]) -> 17-TA1Lon-Lon6/6
A198: London Blues Fest | B198: London | C198: 42892 | D198: Festival | E198: 198 | F198: =IFERROR(VLOOKUP(E198,Margins!$A:$B,2,TRUE),"") -> 0.15 | G198: =IFERROR(E198*F198*I198,"") -> 2227500 | H198: GA3 | I198: 75000 | J198: =IF(Table1[[#This Row],[Tickets Sold]]>500,8,5) -> 8 | K198: 45750 | L198: =VLOOKUP(H198,Descriptions!A:B, 2, FALSE) -> General Admission (season ticket) | M198: =NETWORKDAYS(TODAY(), C198-1) -> -2304 | O198: =RIGHT(YEAR(Table1[[#This Row],[Event Date]]),2)&"-"&Table1[[#This Row],[Ticket Category]]&LEFT(Table1[[#This Row],[Event]],3)&"-"&LEFT(Table1[[#This Row],[City]],3)&DAY(Table1[[#This Row],[Event Date]])&"/"&MONTH(Table1[[#This Row],[Event Date]]) -> 17-GA3Lon-Lon6/6
A199: London Blues Fest | B199: London | C199: 42892 | D199: Festival | E199: 377 | F199: =IFERROR(VLOOKUP(E199,Margins!$A:$B,2,TRUE),"") -> 0.25 | G199: =IFERROR(E199*F199*I199,"") -> 28275 | H199: TA2 | I199: 300 | J199: =IF(Table1[[#This Row],[Tickets Sold]]>500,8,5) -> 5 | K199: 255 | L199: =VLOOKUP(H199,Descriptions!A:B, 2, FALSE) -> Ticket + Air travel + Hotel Package | M199: =NETWORKDAYS(TODAY(), C199-1) -> -2304 | O199: =RIGHT(YEAR(Table1[[#This Row],[Event Date]]),2)&"-"&Table1[[#This Row],[Ticket Category]]&LEFT(Table1[[#This Row],[Event]],3)&"-"&LEFT(Table1[[#This Row],[City]],3)&DAY(Table1[[#This Row],[Event Date]])&"/"&MONTH(Table1[[#This Row],[Event Date]]) -> 17-TA2Lon-Lon6/6
A200: Mark Rodgers | B200: Barcelona | C200: 42931 | D200: Concert | E200: 80 | F200: =IFERROR(VLOOKUP(E200,Margins!$A:$B,2,TRUE),"") -> 0.1 | G200: =IFERROR(E200*F200*I200,"") -> 85264 | H200: GA1 | I200: 10658 | J200: =IF(Table1[[#This Row],[Tickets Sold]]>500,8,5) -> 8 | K200: 6076 | L200: =VLOOKUP(H200,Descriptions!A:B, 2, FALSE) -> General Admission (1 day) | M200: =NETWORKDAYS(TODAY(), C200-1) -> -2275 | O200: =RIGHT(YEAR(Table1[[#This Row],[Event Date]]),2)&"-"&Table1[[#This Row],[Ticket Category]]&LEFT(Table1[[#This Row],[Event]],3)&"-"&LEFT(Table1[[#This Row],[City]],3)&DAY(Table1[[#This Row],[Event Date]])&"/"&MONTH(Table1[[#This Row],[Event Date]]) -> 17-GA1Mar-Bar15/7
A201: Mark Rodgers | B201: Paris | C201: 42942 | D201: Concert | E201: 60 | F201: =IFERROR(VLOOKUP(E201,Margins!$A:$B,2,TRUE),"") -> 0.1 | G201: =IFERROR(E201*F201*I201,"") -> 72294 | H201: GA1 | I201: 12049 | J201: =IF(Table1[[#This Row],[Tickets Sold]]>500,8,5) -> 8 | K201: 6025 | L201: =VLOOKUP(H201,Descriptions!A:B, 2, FALSE) -> General Admission (1 day) | M201: =NETWORKDAYS(TODAY(), C201-1) -> -2268 | O201: =RIGHT(YEAR(Table1[[#This Row],[Event Date]]),2)&"-"&Table1[[#This Row],[Ticket Category]]&LEFT(Table1[[#This Row],[Event]],3)&"-"&LEFT(Table1[[#This Row],[City]],3)&DAY(Table1[[#This Row],[Event Date]])&"/"&MONTH(Table1[[#This Row],[Event Date]]) -> 17-GA1Mar-Par26/7
A202: Mark Rodgers | B202: London | C202: 42957 | D202: Concert | E202: 45 | F202: =IFERROR(VLOOKUP(E202,Margins!$A:$B,2,TRUE),"") -> 0.07 | G202: =IFERROR(E202*F202*I202,"") -> 27915.3 | H202: GA1 | I202: 8862 | J202: =IF(Table1[[#This Row],[Tickets Sold]]>500,8,5) -> 8 | K202: 7445 | L202: =VLOOKUP(H202,Descriptions!A:B, 2, FALSE) -> General Admission (1 day) | M202: =NETWORKDAYS(TODAY(), C202-1) -> -2257 | O202: =RIGHT(YEAR(Table1[[#This Row],[Event Date]]),2)&"-"&Table1[[#This Row],[Ticket Category]]&LEFT(Table1[[#This Row],[Event]],3)&"-"&LEFT(Table1[[#This Row],[City]],3)&DAY(Table1[[#This Row],[Event Date]])&"/"&MONTH(Table1[[#This Row],[Event Date]]) -> 17-GA1Mar-Lon10/8
A203: Mark Rodgers | B203: Hamburg | C203: 42963 | D203: Concert | E203: 30 | F203: =IFERROR(VLOOKUP(E203,Margins!$A:$B,2,TRUE),"") -> 0.07 | G203: =IFERROR(E203*F203*I203,"") -> 26418 | H203: GA1 | I203: 12580 | J203: =IF(Table1[[#This Row],[Tickets Sold]]>500,8,5) -> 8 | K203: 8177 | L203: =VLOOKUP(H203,Descriptions!A:B, 2, FALSE) -> General Admission (1 day) | M203: =NETWORKDAYS(TODAY(), C203-1) -> -2253 | O203: =RIGHT(YEAR(Table1[[#This Row],[Event Date]]),2)&"-"&Table1[[#This Row],[Ticket Category]]&LEFT(Table1[[#This Row],[Event]],3)&"-"&LEFT(Table1[[#This Row],[City]],3)&DAY(Table1[[#This Row],[Event Date]])&"/"&MONTH(Table1[[#This Row],[Event Date]]) -> 17-GA1Mar-Ham16/8
A204: Mark Rodgers | B204: Edinburgh | C204: 42967 | D204: Concert | E204: 60 | F204: =IFERROR(VLOOKUP(E204,Margins!$A:$B,2,TRUE),"") -> 0.1 | G204: =IFERROR(E204*F204*I204,"") -> 58494 | H204: GA1 | I204: 9749 | J204: =IF(Table1[[#This Row],[Tickets Sold]]>500,8,5) -> 8 | K204: 7507 | L204: =VLOOKUP(H204,Descriptions!A:B, 2, FALSE) -> General Admission (1 day) | M204: =NETWORKDAYS(TODAY(), C204-1) -> -2249 | O204: =RIGHT(YEAR(Table1[[#This Row],[Event Date]]),2)&"-"&Table1[[#This Row],[Ticket Category]]&LEFT(Table1[[#This Row],[Event]],3)&"-"&LEFT(Table1[[#This Row],[City]],3)&DAY(Table1[[#This Row],[Event Date]])&"/"&MONTH(Table1[[#This Row],[Event Date]]) -> 17-GA1Mar-Edi20/8
A205: Midnight Soul | B205: Madrid | C205: 42889 | D205: Concert | E205: 74 | F205: =IFERROR(VLOOKUP(E205,Margins!$A:$B,2,TRUE),"") -> 0.1 | G205: =IFERROR(E205*F205*I205,"") -> 50712.2 | H205: GA1 | I205: 6853 | J205: =IF(Table1[[#This Row],[Tickets Sold]]>500,8,5) -> 8 | K205: 4181 | L205: =VLOOKUP(H205,Descriptions!A:B, 2, FALSE) -> General Admission (1 day) | M205: =NETWORKDAYS(TODAY(), C205-1) -> -2305 | O205: =RIGHT(YEAR(Table1[[#This Row],[Event Date]]),2)&"-"&Table1[[#This Row],[Ticket Category]]&LEFT(Table1[[#This Row],[Event]],3)&"-"&LEFT(Table1[[#This Row],[City]],3)&DAY(Table1[[#This Row],[Event Date]])&"/"&MONTH(Table1[[#This Row],[Event Date]]) -> 17-GA1Mid-Mad3/6
A206: Midnight Soul | B206: Stockholm | C206: 42892 | D206: Concert | E206: 61 | F206: =IFERROR(VLOOKUP(E206,Margins!$A:$B,2,TRUE),"") -> 0.1 | G206: =IFERROR(E206*F206*I206,"") -> 72907.2 | H206: GA1 | I206: 11952 | J206: =IF(Table1[[#This Row],[Tickets Sold]]>500,8,5) -> 8 | K206: 9443 | L206: =VLOOKUP(H206,Descriptions!A:B, 2, FALSE) -> General Admission (1 day) | M206: =NETWORKDAYS(TODAY(), C206-1) -> -2304 | O206: =RIGHT(YEAR(Table1[[#This Row],[Event Date]]),2)&"-"&Table1[[#This Row],[Ticket Category]]&LEFT(Table1[[#This Row],[Event]],3)&"-"&LEFT(Table1[[#This Row],[City]],3)&DAY(Table1[[#This Row],[Event Date]])&"/"&MONTH(Table1[[#This Row],[Event Date]]) -> 17-GA1Mid-Sto6/6
... A493: We will roll you | B493: Paris | C493: 42924 | D493: Musical | E493: 400 | F493: =IFERROR(VLOOKUP(E493,Margins!$A:$B,2,TRUE),"") -> 0.4 | G493: =IFERROR(E493*F493*I493,"") -> 64000 | H493: TA2 | I493: 400 | J493: =IF(Table1[[#This Row],[Tickets Sold]]>500,8,5) -> 5 | K493: 356 | L493: =VLOOKUP(H493,Descriptions!A:B, 2, FALSE) -> Ticket + Air travel + Hotel Package | M493: =NETWORKDAYS(TODAY(), C493-1) -> -2280 | O493: =RIGHT(YEAR(Table1[[#This Row],[Event Date]]),2)&"-"&Table1[[#This Row],[Ticket Category]]&LEFT(Table1[[#This Row],[Event]],3)&"-"&LEFT(Table1[[#This Row],[City]],3)&DAY(Table1[[#This Row],[Event Date]])&"/"&MONTH(Table1[[#This Row],[Event Date]]) -> 17-TA2We -Par8/7

Sheet Pivot
A1: City | B1: (All)
A3: Sum of Tickets Sold | B3: Column Labels
A4: Row Labels | B4: GA1 | C4: GA2 | D4: GA3 | E4: POS | F4: SC1 | G4: SC2 | H4: SC3 | I4: SCD | J4: TA1 | K4: TA2 | L4: Grand Total
A5: Ballet | E5: 81 | F5: 2697 | G5: 1644 | H5: 876 | I5: 214 | J5: 1176 | K5: 968 | L5: 7656
A6: Jun | F6: 1125 | G6: 687 | H6: 532 | I6: 98 | J6: 489 | K6: 395 | L6: 3326
A7: Jul | F7: 570 | G7: 353 | H7: 160 | I7: 35 | J7: 246 | K7: 186 | L7: 1550
A8: Aug | E8: 81 | F8: 1002 | G8: 604 | H8: 184 | I8: 81 | J8: 441 | K8: 387 | L8: 2780
A9: Classical | E9: 201 | F9: 6193 | G9: 1861 | H9: 863 | I9: 168 | J9: 1152 | K9: 1112 | L9: 11550
A10: Jun | E10: 94 | F10: 3049 | G10: 628 | H10: 264 | I10: 49 | J10: 264 | K10: 164 | L10: 4512
A11: Jul | E11: 107 | F11: 2147 | G11: 953 | H11: 400 | I11: 69 | J11: 720 | K11: 756 | L11: 5152
A12: Aug | F12: 997 | G12: 280 | H12: 199 | I12: 50 | J12: 168 | K12: 192 | L12: 1886
A13: Concert | B13: 229484 | F13: 16190 | G13: 3584 | J13: 4318 | K13: 4308 | L13: 257884
A14: Jun | B14: 42043 | F14: 3497 | G14: 540 | J14: 701 | K14: 556 | L14: 47337
A15: Jul | B15: 81821 | F15: 6194 | G15: 2454 | J15: 1887 | K15: 1619 | L15: 93975
A16: Aug | B16: 105620 | F16: 6499 | G16: 590 | J16: 1730 | K16: 2133 | L16: 116572
A17: Festival | B17: 1299300 | C17: 206000 | D17: 160500 | E17: 323 | F17: 39342 | G17: 3606 | H17: 255 | I17: 1107 | J17: 3595 | K17: 2924 | L17: 1716952
A18: Jun | B18: 328850 | D18: 127500 | F18: 11681 | G18: 1410 | H18: 255 | I18: 275 | J18: 797 | K18: 714 | L18: 471482
A19: Jul | B19: 817950 | C19: 206000 | D19: 33000 | E19: 323 | F19: 22083 | G19: 1952 | I19: 771 | J19: 2276 | K19: 1745 | L19: 1086100
A20: Aug | B20: 152500 | F20: 5578 | G20: 244 | I20: 61 | J20: 522 | K20: 465 | L20: 159370
A21: Musical | B21: 27437 | E21: 199 | F21: 14443 | G21: 8611 | H21: 1637 | J21: 2559 | K21: 2725 | L21: 57611
A22: Jun | B22: 17689 | F22: 5096 | G22: 3592 | H22: 1114 | J22: 1100 | K22: 1178 | L22: 29769
A23: Jul | B23: 9748 | E23: 87 | F23: 4843 | G23: 2889 | H23: 523 | J23: 496 | K23: 743 | L23: 19329
A24: Aug | E24: 112 | F24: 4504 | G24: 2130 | J24: 963 | K24: 804 | L24: 8513
A25: Opera | E25: 414 | F25: 26883 | G25: 9213 | H25: 3670 | I25: 127 | J25: 2677 | K25: 2699 | L25: 45683
A26: Jun | E26: 55 | F26: 9370 | G26: 3411 | H26: 1416 | J26: 865 | K26: 921 | L26: 16038
A27: Jul | E27: 90 | F27: 10395 | G27: 3551 | H27: 932 | I27: 76 | J27: 604 | K27: 689 | L27: 16337
A28: Aug | E28: 269 | F28: 7118 | G28: 2251 | H28: 1322 | I28: 51 | J28: 1208 | K28: 1089 | L28: 13308
A29: Theatre | E29: 229 | F29: 7016 | G29: 1573 | H29: 489 | I29: 184 | J29: 2129 | K29: 1997 | L29: 13617
A30: Jun | E30: 140 | F30: 3331 | G30: 413 | I30: 91 | J30: 776 | K30: 815 | L30: 5566
A31: Jul | E31: 89 | F31: 2779 | G31: 912 | H31: 489 | I31: 93 | J31: 1077 | K31: 942 | L31: 6381
A32: Aug | F32: 906 | G32: 248 | J32: 276 | K32: 240 | L32: 1670
A33: Grand Total | B33: 1556221 | C33: 206000 | D33: 160500 | E33: 1447 | F33: 112764 | G33: 30092 | H33: 7790 | I33: 1800 | J33: 17606 | K33: 16733 | L33: 2110953

Sheet Calculation 
A1: Genre | B1: Avg % of Sales | C1: Total Margin €
A2: Opera | B2: {=IFERROR(SUMPRODUCT((Events!$D$2:$D$493="Opera")*(MONTH(Events!$C$2:$C$493)=7)*Events!$K$2:$K$493)/SUMPRODUCT((Events!$D$2:$D$493="Opera")*(MONTH(Events!$C$2:$C$493)=7)*Events!$I$2:$I$493),"")} -> 0.75466556 | C2: {=SUMPRODUCT((Events!$D$2:$D$493="Opera")*(MONTH(Events!$C$2:$C$493)=7)*IF(ISNUMBER(Events!$G$2:$G$493),Events!$G$2:$G$493,0))} -> 290221.8
A3: Musical | B3: {=IFERROR(SUMPRODUCT((Events!$D$2:$D$493="Musical")*(MONTH(Events!$C$2:$C$493)=7)*Events!$K$2:$K$493)/SUMPRODUCT((Events!$D$2:$D$493="Musical")*(MONTH(Events!$C$2:$C$493)=7)*Events!$I$2:$I$493),"")} -> 0.78005569 | C3: {=SUMPRODUCT((Events!$D$2:$D$493="Musical")*(MONTH(Events!$C$2:$C$493)=7)*IF(ISNUMBER(Events!$G$2:$G$493),Events!$G$2:$G$493,0))} -> 324954.62
A4: Concert | B4: {=IFERROR(SUMPRODUCT((Events!$D$2:$D$493="Concert")*(MONTH(Events!$C$2:$C$493)=7)*Events!$K$2:$K$493)/SUMPRODUCT((Events!$D$2:$D$493="Concert")*(MONTH(Events!$C$2:$C$493)=7)*Events!$I$2:$I$493),"")} -> 0.68882992 | C4: {=SUMPRODUCT((Events!$D$2:$D$493="Concert")*(MONTH(Events!$C$2:$C$493)=7)*IF(ISNUMBER(Events!$G$2:$G$493),Events!$G$2:$G$493,0))} -> 1094070.8
A5: Festival | B5: {=IFERROR(SUMPRODUCT((Events!$D$2:$D$493="Festival")*(MONTH(Events!$C$2:$C$493)=7)*Events!$K$2:$K$493)/SUMPRODUCT((Events!$D$2:$D$493="Festival")*(MONTH(Events!$C$2:$C$493)=7)*Events!$I$2:$I$493),"")} -> 0.7309365 | C5: {=SUMPRODUCT((Events!$D$2:$D$493="Festival")*(MONTH(Events!$C$2:$C$493)=7)*IF(ISNUMBER(Events!$G$2:$G$493),Events!$G$2:$G$493,0))} -> 9832497.2
A6: Classical | B6: {=IFERROR(SUMPRODUCT((Events!$D$2:$D$493="Classical")*(MONTH(Events!$C$2:$C$493)=7)*Events!$K$2:$K$493)/SUMPRODUCT((Events!$D$2:$D$493="Classical")*(MONTH(Events!$C$2:$C$493)=7)*Events!$I$2:$I$493),"")} -> 0.71013094 | C6: {=SUMPRODUCT((Events!$D$2:$D$493="Classical")*(MONTH(Events!$C$2:$C$493)=7)*IF(ISNUMBER(Events!$G$2:$G$493),Events!$G$2:$G$493,0))} -> 170351.8
A7: Ballet | B7: {=IFERROR(SUMPRODUCT((Events!$D$2:$D$493="Ballet")*(MONTH(Events!$C$2:$C$493)=7)*Events!$K$2:$K$493)/SUMPRODUCT((Events!$D$2:$D$493="Ballet")*(MONTH(Events!$C$2:$C$493)=7)*Events!$I$2:$I$493),"")} -> 0.76317085 | C7: {=SUMPRODUCT((Events!$D$2:$D$493="Ballet")*(MONTH(Events!$C$2:$C$493)=7)*IF(ISNUMBER(Events!$G$2:$G$493),Events!$G$2:$G$493,0))} -> 56431.11
A8: Theater | B8: {=IFERROR(SUMPRODUCT((Events!$D$2:$D$493="Theatre")*(MONTH(Events!$C$2:$C$493)=7)*Events!$K$2:$K$493)/SUMPRODUCT((Events!$D$2:$D$493="Theatre")*(MONTH(Events!$C$2:$C$493)=7)*Events!$I$2:$I$493),"")} -> 0.71455767 | C8: {=SUMPRODUCT((Events!$D$2:$D$493="Theatre")*(MONTH(Events!$C$2:$C$493)=7)*IF(ISNUMBER(Events!$G$2:$G$493),Events!$G$2:$G$493,0))} -> 246292.1
A9: Total | B9: {=IFERROR(SUMPRODUCT((MONTH(Events!$C$2:$C$493)=7)*Events!$K$2:$K$493)/SUMPRODUCT((MONTH(Events!$C$2:$C$493)=7)*Events!$I$2:$I$493),"")} -> 0.72841991 | C9: =SUM(C2:C8) -> 12014819

Sheet Descriptions
A1: Code | B1: Description
A2: TA1 | B2: Ticket + Air travel Package
A3: TA2 | B3: Ticket + Air travel + Hotel Package
A4: GA1 | B4: General Admission (1 day)
A5: GA2 | B5: General Admission (2 days)
A6: GA3 | B6: General Admission (season ticket)
A7: SC1 | B7: Seating Cat. 1
A8: SC2 | B8: Seating Cat. 2
A9: SC3 | B9: Seating Cat. 3
A10: SCD | B10: Seating-disabled
A11: POS | B11: Parking place

Sheet Margins
A1: Ticket Price (euro) | B1: Percentage Turnover Margin
A2: 0 | B2: 0.07
A3: 50 | B3: 0.1
A4: 100 | B4: 0.15
A5: 200 | B5: 0.25
A6: 400 | B6: 0.4
